lazr.enum-1.2.2-py3.13-nspkg.pth
lazr/enum/__init__.py
lazr/enum/_enum.py
lazr/enum/_json.py
lazr/enum/configure.zcml
lazr/enum/interfaces.py
lazr/enum/docs/CONTRIBUTING.rst
lazr/enum/docs/Makefile
lazr/enum/docs/NEWS.rst
lazr/enum/docs/index.rst
lazr/enum/tests/__init__.py
lazr/enum/tests/test_docs.py
lazr/enum/tests/test_proxy.py
lazr.enum-1.2.2.dist-info/COPYING.txt
lazr.enum-1.2.2.dist-info/METADATA
lazr.enum-1.2.2.dist-info/WHEEL
lazr.enum-1.2.2.dist-info/namespace_packages.txt
lazr.enum-1.2.2.dist-info/top_level.txt
lazr.enum-1.2.2.dist-info/RECORD
