Metadata-Version: 2.1
Name: lazr.enum
Version: 1.2.2
Summary: Enums with zope.schema vocabulary support and database-friendly conveniences.
Home-page: https://launchpad.net/lazr.enum
Download-URL: https://launchpad.net/lazr.enum/+download
Maintainer: LAZR Developers
Maintainer-email: lazr-developers@lists.launchpad.net
License: LGPL v3
Project-URL: Source, https://code.launchpad.net/lazr.enum
Project-URL: Issue Tracker, https://bugs.launchpad.net/lazr.enum
Project-URL: Documentation, https://lazrenum.readthedocs.io/en/latest/
Classifier: Development Status :: 5 - Production/Stable
Classifier: Intended Audience :: Developers
Classifier: License :: OSI Approved :: GNU Library or Lesser General Public License (LGPL)
Classifier: Operating System :: OS Independent
Classifier: Programming Language :: Python
Classifier: Programming Language :: Python :: 3
Classifier: Programming Language :: Python :: 3.8
Classifier: Programming Language :: Python :: 3.9
Classifier: Programming Language :: Python :: 3.10
Classifier: Programming Language :: Python :: 3.11
Classifier: Programming Language :: Python :: 3.12
Classifier: Programming Language :: Python :: 3.13
License-File: COPYING.txt
Requires-Dist: importlib-metadata; python_version < "3.8"
Requires-Dist: setuptools
Requires-Dist: six
Requires-Dist: zope.interface>=3.6.0
Requires-Dist: zope.schema
Provides-Extra: proxy
Requires-Dist: zope.security; extra == "proxy"
Provides-Extra: docs
Requires-Dist: Sphinx; extra == "docs"
Provides-Extra: test
Requires-Dist: zope.testrunner; extra == "test"
